archclean/__init__.py
archclean/analyzer.py
archclean/cleaners/__init__.py
archclean/cleaners/home.py
archclean/cleaners/languages.py
archclean/cleaners/system.py
archclean/cli.py
archclean/tracker.py
archclean/tui_analyzer.py
archclean/utils.py
archclean-0.1.13.dist-info/METADATA
archclean-0.1.13.dist-info/WHEEL
archclean-0.1.13.dist-info/entry_points.txt
archclean-0.1.13.dist-info/RECORD
