Metadata-Version: 2.4
Name: archclean
Version: 0.1.13
Summary: A CLI tool for safely cleaning Arch Linux systems.
Author: Raj singh chauhan
Author-email: rajsinghchauhan352@gmail.com
Requires-Python: >=3.13,<4.0
Classifier: Programming Language :: Python :: 3
Classifier: Programming Language :: Python :: 3.13
Classifier: Programming Language :: Python :: 3.14
Requires-Dist: click (>=8.1.7,<9.0.0)
Requires-Dist: rich (>=14.2.0,<15.0.0)
Requires-Dist: sh (>=2.0.6,<3.0.0)
Requires-Dist: textual (>=7.0.0,<8.0.0)
